satcat/__init__.py
satcat/cli/__init__.py
satcat/cli/create.py
satcat/cli/delete.py
satcat/cli/download.py
satcat/cli/get.py
satcat/cli/list.py
satcat/cli/main.py
satcat/cli/submit.py
satcat/cli/update.py
satcat/cli/utils.py
satcat/cli/wait.py
satcat/sdk/__init__.py
satcat/sdk/client.py
satcat/sdk/events/__init__.py
satcat/sdk/events/event_client.py
satcat/sdk/events/models.py
satcat/sdk/maneuvers/cola_maneuver_client.py
satcat/sdk/maneuvers/models.py
satcat/sdk/mission_planning/__init__.py
satcat/sdk/mission_planning/mission_planning_client.py
satcat/sdk/mission_planning/models.py
satcat/sdk/models.py
satcat/sdk/od_client.py
satcat/sdk/propagation/__init__.py
satcat/sdk/propagation/models.py
satcat/sdk/propagation/propagation_client.py
satcat/sdk/screening/__init__.py
satcat/sdk/screening/models.py
satcat/sdk/screening/screening_client.py
satcat/sdk/settings.py
satcat/sdk/utils.py
satcat-1.4.1.dist-info/METADATA
satcat-1.4.1.dist-info/WHEEL
satcat-1.4.1.dist-info/entry_points.txt
satcat-1.4.1.dist-info/RECORD
