Metadata-Version: 2.1
Name: satcat
Version: 1.4.1
Summary: Satcat Software Development Kit by Kayhan Space
License: Apache-2.0
Author: Derek Strobel
Author-email: derek@kayhan.space
Requires-Python: >=3.8,<4
Classifier: License :: OSI Approved :: Apache Software License
Classifier: Programming Language :: Python :: 3
Classifier: Programming Language :: Python :: 3.8
Classifier: Programming Language :: Python :: 3.9
Classifier: Programming Language :: Python :: 3.10
Classifier: Programming Language :: Python :: 3.11
Requires-Dist: pydantic (>1.10.16,<3)
Requires-Dist: python-dotenv (>=0.20.0)
Requires-Dist: requests (>=2.28,<3.0)
Requires-Dist: typer[all] (>=0.6.1,<0.7.0)
